secure_email/__init__.py
secure_email/sendmail.py
secure_email-1.0.5.dist-info/licenses/LICENSE
secure_email-1.0.5.dist-info/WHEEL
secure_email-1.0.5.dist-info/METADATA
secure_email-1.0.5.dist-info/RECORD
