Metadata-Version: 2.4
Name: secure-email
Version: 1.0.5
Summary: This project allows sending STMP email over TLS using SSL.
Author-email: John Dyer <johndyer@lacsd.org>
Classifier: License :: OSI Approved :: MIT License
License-File: LICENSE
